chat_terminal/__init__.py
chat_terminal/app.py
chat_terminal/chat_terminal.py
chat_terminal/server.py
chat_terminal/settings.py
chat_terminal/libs/text_completion_endpoint.py
chat_terminal/utils/__init__.py
chat_terminal/utils/configs.py
chat_terminal/utils/debug_mode.py
chat_terminal/utils/logging.py
chat_terminal/utils/misc.py
ask_terminal-0.1.4.dist-info/LICENSE
ask_terminal-0.1.4.dist-info/METADATA
ask_terminal-0.1.4.dist-info/WHEEL
ask_terminal-0.1.4.dist-info/entry_points.txt
ask_terminal-0.1.4.dist-info/top_level.txt
ask_terminal-0.1.4.dist-info/RECORD
