Metadata-Version: 2.1
Name: ask-terminal
Version: 0.1.4
Summary: Chat with your terminal, getting things done using natural langauge.
Author-email: Dongning Chen <donny.hikari@gmail.com>
License: GNU AFFERO GENERAL PUBLIC LICENSE
Project-URL: Homepage, https://github.com/donny-hikari/chat-terminal
Project-URL: Repository, https://github.com/donny-hikari/chat-terminal
Classifier: Programming Language :: Python :: 3
Classifier: Operating System :: OS Independent
Requires-Python: >=3.10.12
License-File: LICENSE
Requires-Dist: pyyaml>=5.1
Requires-Dist: fastapi>=0.115.2
Requires-Dist: uvicorn>=0.31.1
Requires-Dist: pydantic>=2.5.3
Requires-Dist: mext-lang>=0.1.1
Requires-Dist: aiohttp>=3.9.1
Requires-Dist: transformers>=4.36.2
Requires-Dist: openai>=1.7.1
Requires-Dist: anthropic>=0.36.2
